multiuploader/__init__.py
multiuploader/admin.py
multiuploader/context_processors.py
multiuploader/default_settings.py
multiuploader/forms.py
multiuploader/models.py
multiuploader/urls.py
multiuploader/utils.py
multiuploader/views.py
multiuploader/management/__init__.py
multiuploader/management/commands/__init__.py
multiuploader/management/commands/clean_uploads.py
multiuploader/management/commands/clear_sorlthumbnails.py
multiuploader/migrations/0001_initial.py
multiuploader/migrations/__init__.py
multiuploader/templatetags/__init__.py
multiuploader/templatetags/multiuploader.py
multiuploader/templatetags/verbatim.py
multiuploader-0.1.3.1.dist-info/DESCRIPTION.rst
multiuploader-0.1.3.1.dist-info/METADATA
multiuploader-0.1.3.1.dist-info/RECORD
multiuploader-0.1.3.1.dist-info/WHEEL
multiuploader-0.1.3.1.dist-info/metadata.json
multiuploader-0.1.3.1.dist-info/top_level.txt
tests/__init__.py
tests/mocks.py
tests/test_settings.py
tests/tests_forms.py
tests/tests_views.py
