Metadata-Version: 2.0
Name: multiuploader
Version: 0.1.3.1
Summary: Multiuploader - is an application which enable ability to upload multiple files in Django
Home-page: https://github.com/vinaypost/multiuploader
Author: Vinay Kumar
Author-email: vk-sharma@outlook.com
License: LICENSE.txt
Download-URL: https://github.com/vinaypost/multiuploader/archive/0.1.01.tar.gz
Keywords: multiupload,multiuploader,fileupload,mediaupload,imageupload
Platform: OS Independent
Classifier: Development Status :: 4 - Beta
Classifier: Environment :: Web Environment
Classifier: Framework :: Django
Classifier: Intended Audience :: Developers
Classifier: License :: OSI Approved :: BSD License
Classifier: Operating System :: OS Independent
Classifier: Programming Language :: Python
Classifier: Programming Language :: Python :: 2
Classifier: Programming Language :: Python :: 2.7
Classifier: Programming Language :: Python :: 3
Classifier: Programming Language :: Python :: 3.2
Classifier: Programming Language :: Python :: 3.3
Classifier: Programming Language :: Python :: 3.4
Classifier: Programming Language :: Python :: 3.5
Classifier: Topic :: Internet :: WWW/HTTP
Classifier: Topic :: Internet :: WWW/HTTP :: Dynamic Content
Classifier: Topic :: Software Development
Classifier: Topic :: Software Development :: Libraries :: Application Frameworks
Classifier: Topic :: Software Development :: Libraries :: Python Modules
Requires-Dist: django (>=1.10)
Requires-Dist: python-magic (>=0.4.12)
Requires-Dist: sorl-thumbnail (>=12.3)
